{
  "url": "http://www.baomoi.com/Quay-cuong-vi-dich-soi/82/13624302.epi",
  "time": "21/04/2014 22:22",
  "title": "Quay cuồng vì dịch sởi",
  "category": "Tin tức > Sức khỏe ",
  "description": "(HQ Online)- Y, bác sỹ không chỉ ở các bệnh viện (BV) tuyến trung ương mà ngay cả một số BV tuyến huyện của TP Hà Nội đang phải quay cuồng chống dịch sởi.",
  "content": "<tr> <td> <div> <div align='center'> <div> <span class='storyInlinePhoto'><img src='http://www.baohaiquan.vn/images/2014/4/duongngan/Anh%2012%20(2)%20(1).jpg' /></span> </div> </div> <div> Quá tải khiến bệnh nhi và người nhà tràn ra cả hành lang Khoa Nhi- BV Bạch Mai. Ảnh: Thúy Hà </div> </div> <div> <p>Theo ông Trần Minh Điển- Phó Giám đốc BV Nhi Trung ương, trong ngày 20-4, BV có 218 bệnh nhân mắc sởi, trong đó có 82 bệnh nhân thở oxy, 17 bệnh nhi phải thở máy.</p> <p>Ông Phạm Nhật An- Phó Giám đốc BV Nhi Trung ương cho biết, những ngày này lượng công việc của các bác sĩ trong khoa tăng gấp 3 lần do số bệnh nhân quá đông, số bệnh nhân nặng vẫn tiếp tục gia tăng. </p> <p>'Các bác sỹ, y tá điều dưỡng phải làm việc không chỉ 8 tiếng/ngày mà có khi tới 16 tiếng/ngày. Bắt đầu làm việc tại bệnh viện từ 8h sáng nhưng 22h đêm các bác sỹ vẫn phải thăm khám bệnh nhân liên tục. Một ca trực 4-5 y tá có khi phải chăm sóc hơn 200 bệnh nhân', ông An cho biết thêm. </p> <p>Tại Khoa Nhi- BV Bạch Mai, ông Nguyễn Tiến Dũng cho biết, hiện BV có 58- 60 bệnh nhi liên quan đến sởi. Có 5 ca thở máy đang nguy kịch và 3 có nguy cơ sắp phải thở máy. Tính riêng ngày 20-4 đã có 6 ca nhập viện do sởi.</p> <p>Theo một bác sỹ đang công tác tại khoa Nhi, hiện nhân viên không dám nghỉ phép, nghỉ ốm vì quá tải bệnh nhi. Công việc chăm sóc trẻ bình thường vốn đã vất vả, nay áp lực lại tăng lên gấp 2- 3 lần khiến cho y, bác sỹ rất vất vả.</p> <p>Không chỉ tại các BV tuyến Trung ương mà ngay cả tại các BV huyện, trong những ngày dịch sởi hoành hoành, các nhân viên y tế cũng phải quay cuồng chống dịch.</p> <p> </p> <table align='right' width='100%'> <tbody> <tr> <td align='left'></td> </tr> <tr> <td> <p><span><strong>Nên kê thêm giường để giãn bệnh nhân</strong></span></p> <p><span>Sáng ngày 21-4-2014, Bộ trưởng Y tế Nguyễn Thị Kim Tiến đã đi thị sát tình hình phòng chống dịch sởi tại BV Bạch Mai, BV Bệnh Nhiệt đới Trung ương. </span></p> <p><span>Phát biểu tại cuộc 'vi hành' Bộ trưởng nêu lên 4 nguyên nhân khiến cho bệnh nhi tử vong do sởi tăng nhanh thời gian vừa qua (do không tiêm vắc xin, do quá tải BV, do lây nhiễm chéo tại BV, cuối cùng là do thời tiết). Đồng thời, Bộ trưởng yêu cầu các BV nên kê thêm giường bệnh để giãn bệnh nhân đồng thời lưu ý chế độ dinh dưỡng với bệnh nhân sởi để tăng cường sức đề kháng.</span></p> </td> </tr> <tr> <td align='left'></td> </tr> </tbody> </table> Trong ngày 20-4, Bệnh viện đa khoa Hà Đông- Hà Nội đang điều trị cho 52 bệnh nhân sốt phát ban dạng sởi và sởi. Tính từ đầu năm đến nay, bệnh viện đã điều trị cho 123 bệnh nhân. Từ khi bệnh sởi có chiều hướng gia tăng, ngay tại khoa Khám bệnh và khoa Cấp cứu của bệnh viện đã thực hiện việc phân luồng bệnh nhân nghi sởi, đồng thời bố trí riêng một khu vực cách ly điều trị trong khoa Truyền nhiễm. <p></p> <p>Theo đại diện BV, hiện Khoa Truyền nhiễm hiện đang quá tải vì khoa chỉ có 35 giường và phải điều trị cho các bệnh nhân mắc bệnh truyền nhiễm khác, chính vì vậy mà bệnh nhân sởi phải nằm ghép từ 2- 3 trẻ một giường. Mặc dù quá tải nhưng BV luôn đáp ứng đầy đủ các vật tư tiêu hao, thuốc điều trị và tăng cường thêm các trang thiết bị y tế phục vụ cho điều trị, đặc biệt là máy thở.</p> <p>Tại BV Đa khoa Sơn Tây- Hà Nội cũng đã điều trị cho 46 bệnh nhân sốt phát ban dạng sởi và sởi, trong đó có 12 bệnh nhân được xác định dương tính với vi rút sởi. BV cũng đã bố trí 15 giường trong khoa Truyền nhiễm cho điều trị bệnh nhân sởi và hiện tại có 12 bệnh nhân đang nằm điều trị.</p> <p>Tại BV Đa khoa Đức Giang- Hà Nội, từ đầu vụ dịch đến nay đã khám cho 247 bệnh nhân sởi và điều trị nội trú 193 bệnh nhân (trong đó 124 ca trẻ em chủ yếu từ 9 tháng tuổi đến 24 tháng tuổi). Những ngày gần đây, dịch sởi trên địa bàn có chiều hướng gia tăng nên số bệnh nhân vào viện cũng tăng theo, cụ thể ngày 18-4 có 30 bệnh nhân sởi, ngày 19-4 có 34 bệnh nhân, ngày 20-4 có 39 bệnh nhân. </p> <p> </p> <table align='center' bordercolor='#008000' rules='none' width='100%'> <tbody> <tr> <td align='left'> <p><span><em><strong>Tỷ lệ tiêm chủng vẫn thấp</strong></em></span></p> <p><span><em>Ngày 20-4-2014, Bộ Y tế đã công bố danh sách 20 tỉnh, TP có tỷ lệ tiêm vét vắc xin sởi dưới 50%. Trong đó cá biệt có những địa phương mà tỷ lệ tiêm vét vắc xin sởi chỉ đạt 8,21% (Bình Phước), 15,87% (Long An), 18,15% (Cao Bằng), …Tỷ lệ tiêm thấp ở một số địa phương như trên dẫn đến tỷ lệ tiêm vét vắc xin sởi chung của cả nước xuống còn khoảng 57%.</em></span></p> </td> </tr> </tbody> </table> <p></p> </div><br /></td> </tr> <tr> <td align='left'></td> </tr> <tr> <td> <p><span><strong>Nên kê thêm giường để giãn bệnh nhân</strong></span></p> <p><span>Sáng ngày 21-4-2014, Bộ trưởng Y tế Nguyễn Thị Kim Tiến đã đi thị sát tình hình phòng chống dịch sởi tại BV Bạch Mai, BV Bệnh Nhiệt đới Trung ương. </span></p> <p><span>Phát biểu tại cuộc 'vi hành' Bộ trưởng nêu lên 4 nguyên nhân khiến cho bệnh nhi tử vong do sởi tăng nhanh thời gian vừa qua (do không tiêm vắc xin, do quá tải BV, do lây nhiễm chéo tại BV, cuối cùng là do thời tiết). Đồng thời, Bộ trưởng yêu cầu các BV nên kê thêm giường bệnh để giãn bệnh nhân đồng thời lưu ý chế độ dinh dưỡng với bệnh nhân sởi để tăng cường sức đề kháng.</span></p> </td> </tr> <tr> <td align='left'></td> </tr> <tr> <td align='left'> <p><span><em><strong>Tỷ lệ tiêm chủng vẫn thấp</strong></em></span></p> <p><span><em>Ngày 20-4-2014, Bộ Y tế đã công bố danh sách 20 tỉnh, TP có tỷ lệ tiêm vét vắc xin sởi dưới 50%. Trong đó cá biệt có những địa phương mà tỷ lệ tiêm vét vắc xin sởi chỉ đạt 8,21% (Bình Phước), 15,87% (Long An), 18,15% (Cao Bằng), …Tỷ lệ tiêm thấp ở một số địa phương như trên dẫn đến tỷ lệ tiêm vét vắc xin sởi chung của cả nước xuống còn khoảng 57%.</em></span></p> </td> </tr>",
  "key": [
    "sởi",
    "bệnh nhân",
    "bệnh viện",
    "bệnh nhi",
    "điều trị",
    "truyền nhiễm",
    "khoa nhi",
    "quá tải",
    "Vacxin",
    "quay cuồng",
    "bác sĩ",
    "Hàn Quốc",
    "online",
    "Hà Nội",
    "Bệnh Viện Bạch Mai"
  ],
  "trends": [
    {
      "word": "Bạch Dương",
      "weight": "6"
    },
    {
      "word": "Bảo Bình",
      "weight": "6"
    },
    {
      "word": "Bệnh Viện Bạch Mai",
      "weight": "3"
    },
    {
      "word": "Bệnh viện Nhi TW",
      "weight": "1"
    },
    {
      "word": "Bộ trưởng Bộ Y tế",
      "weight": "2"
    },
    {
      "word": "Bộ Y Tế",
      "weight": "1"
    },
    {
      "word": "Cự Giải",
      "weight": "4"
    },
    {
      "word": "cưới",
      "weight": "6"
    },
    {
      "word": "Kim Ngưu",
      "weight": "4"
    },
    {
      "word": "làn da",
      "weight": "2"
    },
    {
      "word": "ly hôn",
      "weight": "4"
    },
    {
      "word": "mắt",
      "weight": "6"
    },
    {
      "word": "minh họa",
      "weight": "6"
    },
    {
      "word": "Nguyễn Chí Thanh",
      "weight": "6"
    },
    {
      "word": "Nguyễn Thị Kim Tiến",
      "weight": "3"
    },
    {
      "word": "Nhân Mã",
      "weight": "6"
    },
    {
      "word": "rubella",
      "weight": "6"
    },
    {
      "word": "Sở Y Tế",
      "weight": "3"
    },
    {
      "word": "Song Ngư",
      "weight": "3"
    },
    {
      "word": "sốt phát ban",
      "weight": "1"
    },
    {
      "word": "Sư Tử",
      "weight": "3"
    },
    {
      "word": "Thiên Bình",
      "weight": "4"
    },
    {
      "word": "Trung tâm Y tế dự phòng",
      "weight": "2"
    },
    {
      "word": "ung thư",
      "weight": "2"
    },
    {
      "word": "ung thư vú",
      "weight": "6"
    },
    {
      "word": "Vacxin",
      "weight": "1"
    },
    {
      "word": "vi khuẩn",
      "weight": "4"
    },
    {
      "word": "virus",
      "weight": "2"
    },
    {
      "word": "Xử Nữ",
      "weight": "6"
    },
    {
      "word": "yêu",
      "weight": "2"
    }
  ]
}
