{
  "url": "http://www.baomoi.com/Vi-sao-HLV-Wenger-re-rung-tran-thang-Hull-City/87/13623171.epi",
  "time": "21/04/2014 20:36",
  "title": "Vì sao HLV Wenger 'rẻ rúng' trận thắng Hull City?",
  "category": "Tin tức > Thể thao > Bóng đá",
  "description": "TPO - HLV Wenger không 'sướng' với trận thắng cách biệt Hull tại Premier League vừa qua. Thậm chí, nhà cầm quân này còn coi đây là 'chiến thắng vô nghĩa' khi hai đội gặp nhau ở chung kết FA Cup.",
  "content": "<tr> <td> <div id='ctl00_mainContent_ctl01_pnPhoto'> <span class='storyInlinePhoto'><img src='http://images.tienphong.vn/Uploaded/tuanduc/2014_04_21/article-1231837-029F3DCF0000044D-420_468x293_NGHV.jpg.ashx?w=660&h=371&crop=auto' /></span> <span>Danh hiệu FA Cup năm 2005 là lần gần đây nhất Arsenal đứng trên bục vinh quang.</span> </div> <div id='article-body'> <p><span>Ở trận thắng Hull vừa qua, Lukas Podolski là người ghi cú đúp sau khi Aaron Ramsey mở điểm cho chiến thắng của đoàn quân <em>The Gunners</em> ngay tại sân KC. Song với HLV Wenger, trận tái đấu ở chung kết FA Cup vào ngày 17/5 sắp tới là hoàn toàn khác: “Chúng kết FA Cup là trận đấu hoàn toàn khác”.</span></p> <p>Trong lịch sử, Arsenal đã từng đăng quang FA Cup năm 1998 và 2003 ngay sau khi đã thắng các đối thủ Newcastle và Southampton ở các trận đấu thuộc khuôn khổ Premier League trước đó. </p> <p>Song mùa trước, Man City gây ngạc nhiên khi bị Wigan đánh bại tại Wembley dù họ vừa thắng đối thủ trong khuôn khổ Premier League cách đó một tuần. </p> <p>Tiền vệ Ramsey, người từng thi đấu cho Cardiff trong trận thua Portsmouth chung kết 2008, cũng thừa nhận: “Chúng tôi đánh bại Hull hai lần nhưng sẽ không dễ dàng để lập lại màn trình diễn trước đó”. </p> <p>Trong trận chung kết sắp tới, Hull bị đánh giá thấp hơn không bởi vì trình độ chênh lệch mà họ cũng sẽ không có được đội hình mạnh nhất. Bộ đôi tiền đạo Nikica Jelavic và Shane Long bị cấm tham dự vì từng đá cho Everton và West Brom hồi đầu mùa.</p> </div><br /></td> </tr>",
  "key": [
    "Hull",
    "Cúp FA",
    "Arsene Wenger",
    "chung kết",
    "trận thắng",
    "Giải ngoại hạng Anh",
    "Arsenal",
    "huấn luyện viên",
    "khuôn khổ",
    "Aaron Ramsey",
    "Hull City",
    "Lukas Podolski",
    "Newcastle",
    "Southampton",
    "Manchester City"
  ],
  "trends": [
    {
      "word": "Arsenal",
      "weight": "1"
    },
    {
      "word": "Barcelona",
      "weight": "2"
    },
    {
      "word": "Becamex Bình Dương",
      "weight": "6"
    },
    {
      "word": "Champions League",
      "weight": "5"
    },
    {
      "word": "Chelsea",
      "weight": "2"
    },
    {
      "word": "David de Gea",
      "weight": "5"
    },
    {
      "word": "David Moyes",
      "weight": "1"
    },
    {
      "word": "Everton",
      "weight": "1"
    },
    {
      "word": "Giải ngoại hạng Anh",
      "weight": "2"
    },
    {
      "word": "Goodison Park",
      "weight": "2"
    },
    {
      "word": "Hull City",
      "weight": "2"
    },
    {
      "word": "José Mourinho",
      "weight": "6"
    },
    {
      "word": "Juan Mata",
      "weight": "6"
    },
    {
      "word": "Lionel Messi",
      "weight": "3"
    },
    {
      "word": "Liverpool",
      "weight": "1"
    },
    {
      "word": "Luis Suarez",
      "weight": "4"
    },
    {
      "word": "Lukas Podolski",
      "weight": "4"
    },
    {
      "word": "Manchester City",
      "weight": "3"
    },
    {
      "word": "Manchester United",
      "weight": "1"
    },
    {
      "word": "Mesut Özil",
      "weight": "4"
    },
    {
      "word": "Phạm Văn Quyến",
      "weight": "6"
    },
    {
      "word": "Quỷ Đỏ",
      "weight": "5"
    },
    {
      "word": "Real Madrid",
      "weight": "3"
    },
    {
      "word": "Santi Cazorla",
      "weight": "6"
    },
    {
      "word": "Shinji Kagawa",
      "weight": "5"
    },
    {
      "word": "Sông Lam Nghệ An",
      "weight": "5"
    },
    {
      "word": "Sunderland",
      "weight": "3"
    },
    {
      "word": "Vinakansai Ninh Bình",
      "weight": "6"
    },
    {
      "word": "Wayne Rooney",
      "weight": "3"
    },
    {
      "word": "Wojciech Tomasz Szczęsny",
      "weight": "5"
    }
  ]
}
